gym_trading_env/__init__.py
gym_trading_env/downloader.py
gym_trading_env/environments.py
gym_trading_env/renderer.py
gym_trading_env/wrapper.py
gym_trading_env/templates/index.html
gym_trading_env/utils/__init__.py
gym_trading_env/utils/charts.py
gym_trading_env/utils/history.py
gym_trading_env/utils/portfolio.py
gym_trading_env_continuous-1.0.2.dist-info/licenses/LICENSE.txt
gym_trading_env_continuous-1.0.2.dist-info/METADATA
gym_trading_env_continuous-1.0.2.dist-info/WHEEL
gym_trading_env_continuous-1.0.2.dist-info/top_level.txt
gym_trading_env_continuous-1.0.2.dist-info/RECORD
