Metadata-Version: 2.4
Name: gym-trading-env-continuous
Version: 1.0.2
Summary: A simple, easy, customizable Gymnasium environment for trading.
Author-email: Remy Chaput <rchaput.pro@gmail.com>, Clement Perroud <clement.perroud.pro@gmail.com>
License: MIT License
Project-URL: Homepage, https://github.com/rchaput/gym-trading-env-continuous
Project-URL: Bug Tracker, https://github.com/rchaput/gym-trading-env-continuous/issues
Classifier: Programming Language :: Python :: 3
Classifier: License :: OSI Approved :: MIT License
Classifier: Operating System :: OS Independent
Requires-Python: >=3.7
License-File: LICENSE.txt
Requires-Dist: pandas>=1.5.3
Requires-Dist: numpy>=1.21.1
Requires-Dist: gymnasium>=0.28.1
Requires-Dist: flask>=2.2.3
Requires-Dist: pyecharts>=2.0.2
Requires-Dist: ccxt==3.0.59
Requires-Dist: nest_asyncio
Dynamic: license-file
